bulma/__init__.py
bulma/apps.py
bulma/management/__init__.py
bulma/management/commands/__init__.py
bulma/management/commands/bulma.py
bulma/management/commands/copy_bulma_static_into_project.py
bulma/static/bulma/css/style.css
bulma/static/bulma/css/style.css.map
bulma/static/bulma/css/style.min.css
bulma/static/bulma/sass/.gitignore
bulma/static/bulma/sass/package-lock.json
bulma/static/bulma/sass/package.json
bulma/static/bulma/sass/style.sass
bulma/templates/_layouts/one-column-center.html
bulma/templates/base.html
bulma/templates/bulma/base.html
bulma/templates/bulma/forms/field.html
bulma/templates/bulma/forms/form.html
bulma/templates/bulma/forms/formset.html
bulma/templates/pagination.html
bulma/templates/registration/base.html
bulma/templates/registration/logged_out.html
bulma/templates/registration/login.html
bulma/templates/registration/password_change_done.html
bulma/templates/registration/password_change_form.html
bulma/templates/registration/password_reset_complete.html
bulma/templates/registration/password_reset_confirm.html
bulma/templates/registration/password_reset_done.html
bulma/templates/registration/password_reset_email.html
bulma/templates/registration/password_reset_form.html
bulma/templatetags/__init__.py
bulma/templatetags/bulma_tags.py
bulma/tests/__init__.py
bulma/tests/conftest.py
bulma/tests/forms.py
bulma/tests/test_commands.py
bulma/tests/test_inputs.py
bulma/tests/test_templates.py
bulma/tests/utils.py
django_bulma-0.10.0.dist-info/LICENSE
django_bulma-0.10.0.dist-info/METADATA
django_bulma-0.10.0.dist-info/WHEEL
django_bulma-0.10.0.dist-info/RECORD
